Metadata-Version: 1.0
Name: tagscounteralexdoka
Version: 0.1.4
Summary: app counting tags on web page
Home-page: UNKNOWN
Author: Aliaksandr Dakutovich
Author-email: alex.doka@gmail.com
License: MIT
Platform: UNKNOWN
